[
  {
    "roll": "2403001",
    "name": "FATIN BIN MONIR",
    "password": "GrAVPOJnto"
  },
  {
    "roll": "2403002",
    "name": "ROHAN AHMED SAMIN",
    "password": "jgqAuv2zVe"
  },
  {
    "roll": "2403003",
    "name": "MD. SADMAN SHAMI",
    "password": "PVKARB1Uzy"
  },
  {
    "roll": "2403004",
    "name": "MD. MOHIDUL ISLAM",
    "password": "erc3iAGerp"
  },
  {
    "roll": "2403005",
    "name": "MD. KAYES AHMED",
    "password": "AZRP6pIdvU"
  },
  {
    "roll": "2403006",
    "name": "MD. EFTEKHAR HASNAT RAHI",
    "password": "bCXf7mNxSf"
  },
  {
    "roll": "2403007",
    "name": "NOUSHIN FARIHA",
    "password": "g5MhpycUww"
  },
  {
    "roll": "2403008",
    "name": "MD. RAHIDUL MOWLA",
    "password": "O96au6vRFn"
  },
  {
    "roll": "2403009",
    "name": "MD. ASHIK E ELAHEE",
    "password": "YcNZYZExWn"
  },
  {
    "roll": "2403010",
    "name": "MD. IMRUL KAYES MONDOL",
    "password": "IhOmVBh9CN"
  },
  {
    "roll": "2403011",
    "name": "MAYEDA RAHMAN MITHI",
    "password": "esVUDddFBf"
  },
  {
    "roll": "2403012",
    "name": "MD. MUHIUDDIN",
    "password": "8OubSmh6Dk"
  },
  {
    "roll": "2403013",
    "name": "MUHAMMAD RAGIB ISHRAK",
    "password": "qNGnmhUjNP"
  },
  {
    "roll": "2403014",
    "name": "GOLAM LABIB RAHMAN MAHI",
    "password": "41nMnAygrJ"
  },
  {
    "roll": "2403015",
    "name": "SAMIUS SALEH",
    "password": "bnyD4X0IIH"
  },
  {
    "roll": "2403016",
    "name": "ZARIN MAHZABIN",
    "password": "7wc3z2fmMq"
  },
  {
    "roll": "2403017",
    "name": "NIRJHAR SHARMILI",
    "password": "9Zy49U88rh"
  },
  {
    "roll": "2403018",
    "name": "TASFIA RAHMAN",
    "password": "86vgA01U7R"
  },
  {
    "roll": "2403019",
    "name": "MD. NAVID HASAN",
    "password": "s1sJh5W2bv"
  },
  {
    "roll": "2403020",
    "name": "SAKIB REZA",
    "password": "PzHDkIXO4V"
  },
  {
    "roll": "2403021",
    "name": "ADNAN ISLAM RAMIM",
    "password": "uMzy4j9prC"
  },
  {
    "roll": "2403022",
    "name": "SADMAN SUBA AHIN",
    "password": "TALTe86JIi"
  },
  {
    "roll": "2403023",
    "name": "MADIHA AKTER",
    "password": "RwWiJm4FUB"
  },
  {
    "roll": "2403024",
    "name": "KAZI IBTESHAMA BANU KHUTBA",
    "password": "LQnpyauU7m"
  },
  {
    "roll": "2403025",
    "name": "FAKID EHSAN",
    "password": "SgbroPdcMp"
  },
  {
    "roll": "2403026",
    "name": "RAHUL TALUKDER",
    "password": "SYkU6yaqvI"
  },
  {
    "roll": "2403027",
    "name": "MD. MAHABUBUR RAHMAN RAIHAN",
    "password": "bV7GLxb47h"
  },
  {
    "roll": "2403028",
    "name": "MD MAHBUBUL HOQUE",
    "password": "JEKUHlyRZ2"
  },
  {
    "roll": "2403029",
    "name": "WARDA AHAMER OHANA",
    "password": "z8t8oeZnNK"
  },
  {
    "roll": "2403030",
    "name": "AATTROLITA IQBAL BAISHAKHY",
    "password": "C5cWrv2BwH"
  },
  {
    "roll": "2403031",
    "name": "HASIBUR RAHMAN",
    "password": "HRt6AtJGUb"
  },
  {
    "roll": "2403032",
    "name": "SYEDA ESTIKA EMAM", 
    "password": "Ulw8WbbSJP"
  },
  {
    "roll": "2403033",
    "name": "MST. SADIA AKTER",
    "password": "u2mW6E53Oi"
  },
  {
    "roll": "2403034",
    "name": "RAFI MAHMUD",
    "password": "cbpeqroCf5"
  },
  {
    "roll": "2403035",
    "name": "SAMUDRO SANYAL",
    "password": "PHrfsjhDt0"
  },
  {
    "roll": "2403036",
    "name": "TAHSIN UL ISLAM ELEM",
    "password": "eggi5ZqQSO"
  },
  {
    "roll": "2403037",
    "name": "MD. AHSAN MOSHAROF",
    "password": "Ao6FjjGv0v"
  },
  {
    "roll": "2403038",
    "name": "OM PROKASH DIBYA",
    "password": "tHPRmoZbcE"
  },
  {
    "roll": "2403039",
    "name": "MD. MAHDI KHAN OMI",
    "password": "qiiSbw2N7Y"
  },
  {
    "roll": "2403040",
    "name": "A. F. M. MAHMUD HASAN NIRJAS",
    "password": "UIgPxaOago"
  },
  {
    "roll": "2403041",
    "name": "FARIHA RAUNOK ARSHI",
    "password": "e3iznQc3Ha"
  },
  {
    "roll": "2403042",
    "name": "OVIJIT DEBNATH",
    "password": "V6Ump0rzb3"
  },
  {
    "roll": "2403043",
    "name": "SHAHRIAR ABDULLAH SEAM",
    "password": "wD5NnkCOZX"
  },
  {
    "roll": "2403044",
    "name": "MD. NAEEM HASAN",
    "password": "CAFLEoab7g"
  },
  {
    "roll": "2403045",
    "name": "MD. GOLAP SAROAR",
    "password": "BwC7CcZlJU"
  },
  {
    "roll": "2403046",
    "name": "PRONOB KUMAR TALUKDER",
    "password": "B5tWD3wX9G"
  },
  {
    "roll": "2403047",
    "name": "RAWFI AKHTAR BOBY",
    "password": "p1hNsUZxs9"
  },
  {
    "roll": "2403048",
    "name": "MD. MAHERAB HOSSEN",
    "password": "pPOTto0ez2"
  },
  {
    "roll": "2403049",
    "name": "MST. MUNTASIN RIMA",
    "password": "mPbDQxB85M"
  },
  {
    "roll": "2403050",
    "name": "MST. MITHILA RAHMAN LIMA",
    "password": "W0zkS0bqB6"
  },
  {
    "roll": "2403051",
    "name": "TANSIM TABASUM SHIFA",
    "password": "rLf0P7URDl"
  },
  {
    "roll": "2403052",
    "name": "SHAIKH JAFIR JOHAIR RAHMAN",
    "password": "c6mK5Dxiu8"
  },
  {
    "roll": "2403053",
    "name": "MINHAJUL KHONDOKAR",
    "password": "ce08wawMYP"
  },
  {
    "roll": "2403054",
    "name": "BIJOY SAHA",
    "password": "LJtZnNz020"
  },
  {
    "roll": "2403055",
    "name": "RAFAT SUJJADA DEWAN",
    "password": "4aD3DMyJVB"
  },
  {
    "roll": "2403056",
    "name": "NILOY CHANDRA DAS",
    "password": "9JsQ2BcJNB"
  },
  {
    "roll": "2403057",
    "name": "SANJID ALAM",
    "password": "3wrdqavWSd"
  },
  {
    "roll": "2403058",
    "name": "MD.SHAMIUL ISLAM",
    "password": "av0Q7iFsOl"
  },
  {
    "roll": "2403059",
    "name": "MD. ASHIF ARAFAT SHITUL",
    "password": "sX75PQantZ"
  },
  {
    "roll": "2403060",
    "name": "ADITA ANAN ORIN",
    "password": "BCnASqmCNU"
  },
  {
        "roll": "2403061",
        "name": "AYMAN ZAMEE",
        "password": "AIe7PwltXM"
    },
    {
        "roll": "2403062",
        "name": "SHEFAUL RASHID",
        "password": "f4SEF0fx2W"
    },
    {
        "roll": "2403063",
        "name": "QUAZI MUHAMMAD MUTTAQEEN",
        "password": "4u5MbHejlH"
    },
    {
        "roll": "2403064",
        "name": "ISRAT JAHAN",
        "password": "VwDDWbTqEM"
    },
    {
        "roll": "2403065",
        "name": "KHANDAKER NAZMUS SAKIB",
        "password": "dhQ3U9K0Hy"
    },
    {
        "roll": "2403066",
        "name": "MD. DAUD KAMRAN MUNNA",
        "password": "JQliOikbhN"
    },
    {
        "roll": "2403067",
        "name": "TANBIR AHOMED SIYAM",
        "password": "PQKG8A3WfI"
    },
    {
        "roll": "2403068",
        "name": "ABIR HOSSAIN",
        "password": "b9eKXlKgSY"
    },
    {
        "roll": "2403069",
        "name": "MD. MAHADI HASAN SHIHAB",
        "password": "iWYU6hX4q6"
    },
    {
        "roll": "2403070",
        "name": "PRANTO SAHA",
        "password": "ISawfvna84"
    },
    {
        "roll": "2403071",
        "name": "SHAH ARIAN",
        "password": "akU8FoAvNx"
    },
    {
        "roll": "2403072",
        "name": "SOURAV SARKER",
        "password": "DLhtTmszTh"
    },
    {
        "roll": "2403073",
        "name": "SANIA RAISA",
        "password": "pgcE5TQNH0"
    },
    {
        "roll": "2403074",
        "name": "SADMAN SAFIN NELOY",
        "password": "SA1xPa0R0g"
    },
    {
        "roll": "2403075",
        "name": "MD. FARDIN ISLAM KHAN",
        "password": "jI0ccN2zqP"
    },
    {
        "roll": "2403076",
        "name": "MD. TUSHER MIA",
        "password": "FVLSuP2ZjU"
    },
    {
        "roll": "2403077",
        "name": "MD. SHAFAYAT ALAM",
        "password": "eMZRcsNGIm"
    },
    {
        "roll": "2403078",
        "name": "SAMIA ISLAM CHAITY",
        "password": "tSYhuuL3u0"
    },
    {
        "roll": "2403079",
        "name": "YEASIR ARAFAT",
        "password": "iiDUObCMuS"
    },
    {
        "roll": "2403080",
        "name": "MD. MAHMUD UL HASAN MAHIM",
        "password": "HykK5HJl42"
    },
    {
        "roll": "2403081",
        "name": "SARIM SADMAN RAFIO",
        "password": "n3mf6X8VtX"
    },
    {
        "roll": "2403082",
        "name": "MUNTASIR AHMED",
        "password": "D4Zbh3dJAD"
    },
    {
        "roll": "2403083",
        "name": "JAMIL HASAN RIJU",
        "password": "H5u1wAfhUl"
    },
    {
        "roll": "2403084",
        "name": "FOUZIA ISLAM",
        "password": "2OqUBWFXng"
    },
    {
        "roll": "2403085",
        "name": "A S M AL-MAHMUD",
        "password": "PgmEv2IRh7"
    },
    {
        "roll": "2403086",
        "name": "MD. SAIDUL ISLAM SAID",
        "password": "jpcwfyY3Ww"
    },
    {
        "roll": "2403087",
        "name": "MD. SHAHRIAR MUSTAQ",
        "password": "mpRI4hZEuk"
    },
    {
        "roll": "2403088",
        "name": "NUSRAT JAHAN SORNA",
        "password": "eZo62RVX7w"
    },
    {
        "roll": "2403089",
        "name": "MD. AL MAMUN",
        "password": "8ohrOu6EiE"
    },
    {
        "roll": "2403090",
        "name": "PRANTA SAHA MUGDHA",
        "password": "wI6pwA7FPX"
    },
    {
        "roll": "2403091",
        "name": "MOJIBUR RAHMAN",
        "password": "cBtKGkKLx1"
    },
    {
        "roll": "2403092",
        "name": "TASNUR AKTER MOULY",
        "password": "waE7ZD1Sp4"
    },
    {
        "roll": "2403093",
        "name": "SHAHRIAR ISLAM DEEP",
        "password": "84dygJzD7x"
    },
    {
        "roll": "2403094",
        "name": "ABIJIT DAS UTSHA",
        "password": "mSjVdLX5P1"
    },
    {
        "roll": "2403095",
        "name": "ABDULLAH AL MUNTASIR",
        "password": "gnQZn5uBOf"
    },
    {
        "roll": "2403096",
        "name": "MD. AFNAN",
        "password": "FFtECHH0TM"
    },
    {
        "roll": "2403097",
        "name": "MD. JAHIN ALAM JIMAN",
        "password": "Nt6JVM1Z9J"
    },
    {
        "roll": "2403098",
        "name": "MOHAMMOD RASHEDUL ISLAM",
        "password": "qIc3c27sea"
    },
    {
        "roll": "2403099",
        "name": "SUJOY ROY SUDIPTO",
        "password": "JtmC2Vbn3H"
    },
    {
        "roll": "2403100",
        "name": "SUPANTHO BISWAS",
        "password": "w7rweOWMnS"
    },
    {
        "roll": "2403101",
        "name": "MD.ARIFUL ISLAM",
        "password": "3PlRLI74qZ"
    },
    {
        "roll": "2403102",
        "name": "ABDULLAH AL MASUM",
        "password": "Mik5OtmoTJ"
    },
    {
        "roll": "2403103",
        "name": "SAMIR IBN ZAKIR",
        "password": "NfMgP582EP"
    },
    {
        "roll": "2403104",
        "name": "ARPITA MONDAL KUMKUM",
        "password": "EDaV2jK5G5"
    },
    {
        "roll": "2403105",
        "name": "SHAJID HASAN JIM",
        "password": "pa3HzV1CNH"
    },
    {
        "roll": "2403106",
        "name": "MD. MAHMODUL HASAN",
        "password": "0knEQfFzE7"
    },
    {
        "roll": "2403107",
        "name": "ROMJAN ALI",
        "password": "rmDAcif5Z1"
    },
    {
        "roll": "2403108",
        "name": "ANUP PAUL",
        "password": "U4xsGyagX3"
    },
    {
        "roll": "2403109",
        "name": "MD. SHAHRIAR ALAM",
        "password": "r9guqILW4Y"
    },
    {
        "roll": "2403110",
        "name": "HIRA RANJAN ROY",
        "password": "o6NtKUN7Is"
    },
    {
        "roll": "2403111",
        "name": "MD. ASHRAFUL ISLAM SIHAB",
        "password": "1VUPoa5mLA"
    },
    {
        "roll": "2403112",
        "name": "ABDULLAH-AL-MAHADI",
        "password": "XSsMXLHulY"
    },
    {
        "roll": "2403113",
        "name": "FARHAD AHAMMED TURKY",
        "password": "EmoHjpgjr9"
    },
    {
        "roll": "2403114",
        "name": "MD. HASAN IMAM",
        "password": "thcAwAtLKS"
    },
    {
        "roll": "2403115",
        "name": "MST. ANIKA RAHMAN",
        "password": "brhAPeI2R2"
    },
    {
        "roll": "2403116",
        "name": "ANTOR MONDOL",
        "password": "99qmD7iquO"
    },
    {
        "roll": "2403117",
        "name": "MD. RATUL HASAN",
        "password": "5iRX3KVmom"
    },
    {
        "roll": "2403118",
        "name": "RODHELA HORE PREONTY",
        "password": "bhWMOsrwU6"
    },
    {
        "roll": "2403119",
        "name": "ABDULLAH HEL SHAFI",
        "password": "K7HpkysjHn"
    },
    {
        "roll": "2403120",
        "name": "MAISHA FARIHA",
        "password": "KDmV167DJC"
    }
,
  {
    "roll": "2403121",
    "name": "MD.TAUSIF AL SAHAD",
    "password": "Mze6IstfWOed"
  },
  {
    "roll": "2403122",
    "name": "MOST. UMME KULSUM",
    "password": "Te7B3ZsKkINM"
  },
  {
    "roll": "2403123",
    "name": "MD AMINUL ISLAM SIFAT",
    "password": "pb0lZWWdmctv"
  },
  {
    "roll": "2403124",
    "name": "YASIR ARAFAT",
    "password": "nQ6F7enamOQ7"
  },
  {
    "roll": "2403125",
    "name": "DEWAN ABID HASAN",
    "password": "CWtMKihVWMlZ"
  },
  {
    "roll": "2403126",
    "name": "AFRA TAHSIN ANIKA",
    "password": "ZemlNHGZS1G4"
  },
  {
    "roll": "2403127",
    "name": "SHADMAN AHMED",
    "password": "kUkmuA3Hx6Br"
  },
  {
    "roll": "2403128",
    "name": "KHUSHBO NAHID",
    "password": "F9NC931FbdTi"
  },
  {
    "roll": "2403129",
    "name": "SUMON MAJUMDER",
    "password": "w5AbID9zHvlC"
  },
  {
    "roll": "2403130",
    "name": "MD. ABDUL MUKIT",
    "password": "TshVPoainkQh"
  },
  {
    "roll": "2403131",
    "name": "ATHAI DEY",
    "password": "SxnRSOQBvqc3"
  },
  {
    "roll": "2403132",
    "name": "TASNUVA TABASSUM AMY",
    "password": "6BFZhUIxr5Pc"
  },
  {
    "roll": "2403133",
    "name": "SHARIQUL ISLAM",
    "password": "ghXmmu3ETRR7"
  },
  {
    "roll": "2403134",
    "name": "URBOSHI MAHMUD",
    "password": "IzYdZIPd30sB"
  },
  {
    "roll": "2403135",
    "name": "MD SHADHIN ALI",
    "password": "2SUXaD1YF9Bl"
  },
  {
    "roll": "2403136",
    "name": "PRANTIK PAUL",
    "password": "0qqgVnxw21uB"
  },
  {
    "roll": "2403137",
    "name": "AFTAB UDDIN",
    "password": "7jyVqbLgjZuS"
  },
  {
    "roll": "2403138",
    "name": "ABDULLAH AL BAKI SIFAT",
    "password": "ALdXIe2C4LEl"
  },
  {
    "roll": "2403139",
    "name": "SUJOY RABIDAS",
    "password": "YAXwxBOi9S4G"
  },
  {
    "roll": "2403140",
    "name": "TASAQUF AHNAF",
    "password": "hvIbTzSyKvHg"
  },
  {
    "roll": "2403141",
    "name": "MD SAJID AHMED",
    "password": "HvZAGssyZLkG"
  },
  {
    "roll": "2403142",
    "name": "BITTO SAHA",
    "password": "NvuaeCx7KVpr"
  },
  {
    "roll": "2403143",
    "name": "MD TASDID HOSSAIN ANTOR",
    "password": "v1V9d4oPfgca"
  },
  {
    "roll": "2403144",
    "name": "IMRAN KABIR FAHAD",
    "password": "aE5z8e6GqyB9"
  },
  {
    "roll": "2403145",
    "name": "MD.NAZMUS SAQUIB SINAN",
    "password": "konA6blfdflS"
  },
  {
    "roll": "2403146",
    "name": "MD RABIB REHMAN",
    "password": "oKyF9bbvlJ3G"
  },
  {
    "roll": "2403147",
    "name": "MD. MIRAJUL ISLAM",
    "password": "GDew5tTQeNp1"
  },
  {
    "roll": "2403148",
    "name": "MD. SAMIUL ISLAM",
    "password": "CIbLnXPm43YW"
  },
  {
    "roll": "2403149",
    "name": "AREFIN NOUSED RATUL",
    "password": "bjNNxVi9PJlt"
  },
  {
    "roll": "2403150",
    "name": "SUPRIO ROY CHOWDHURY",
    "password": "AA0r8ygPdk41"
  },
  {
    "roll": "2403151",
    "name": "SHAFAYET HOSSAIN SHUVO",
    "password": "WQsxmVn0hdNA"
  },
  {
    "roll": "2403152",
    "name": "MD. TANVIR CHOWDHURY",
    "password": "kj6bdiKbbMJq"
  },
  {
    "roll": "2403153",
    "name": "MA SHIBLI SADIK SIHAB",
    "password": "CYS6BEY5dcCU"
  },
  {
    "roll": "2403154",
    "name": "MD. MORCHHALIN ALAM AMIO",
    "password": "FQ3dZYvs6ot5"
  },
  {
    "roll": "2403155",
    "name": "ARNOB BENEDICT TUDU",
    "password": "zGN7lc2U2bVY"
  },
  {
    "roll": "2403156",
    "name": "MD. SHOYKOT MOLLA",
    "password": "h7zSoKtju70C"
  },
  {
    "roll": "2403157",
    "name": "MD.TAHMIM ULLAH",
    "password": "69gD0sGyl8GT"
  },
  {
    "roll": "2403158",
    "name": "MD. SAROAR JAHAN TIUS",
    "password": "ulcHFUNHG9dT"
  },
  {
    "roll": "2403159",
    "name": "TAFSIRUL AHMED AZAN",
    "password": "rFSc7b1dl21X"
  },
  {
    "roll": "2403160",
    "name": "NILAY PAUL PARTHA",
    "password": "B5P1R0lqTEbJ"
  },
  {
    "roll": "2403161",
    "name": "MD. FAZLA HASSAN RABBI",
    "password": "kkRpJl3J7v4Q"
  },
  {
    "roll": "2403162",
    "name": "SALMAN AHMED SABBIR",
    "password": "ECXRmtcjrVpQ"
  },
  {
    "roll": "2403163",
    "name": "MD TANVIR AHMED",
    "password": "rFCJ6My8Eix1"
  },
  {
    "roll": "2403164",
    "name": "MOINUDDIN KABIR",
    "password": "tX37HQDYrPuP"
  },
  {
    "roll": "2403165",
    "name": "AVIJET CHAKRABORTY",
    "password": "fuXw4BhhgZRM"
  },
  {
    "roll": "2403166",
    "name": "MD. SAMI SADIK",
    "password": "kKQQx8QNlNlg"
  },
  {
    "roll": "2403167",
    "name": "MD.MEHEDI HASAN",
    "password": "l3EQb8TdylRo"
  },
  {
    "roll": "2403168",
    "name": "MD.TASNIMUL HASAN",
    "password": "XO227xQoahWW"
  },
  {
    "roll": "2403169",
    "name": "MD. MUBINUR RAHMAN",
    "password": "UXhe05DPb99K"
  },
  {
    "roll": "2403170",
    "name": "ESIKA TANZUM YAME",
    "password": "7Xl9fpYY6xOt"
  },
  {
    "roll": "2403171",
    "name": "MD. SAZEDUL ISLAM SUNNY",
    "password": "nQLnXtVe8b8U"
  },
  {
    "roll": "2403172",
    "name": "MD FAZLE RABBI",
    "password": "qlfLNPENDUqF"
  },
  {
    "roll": "2403173",
    "name": "SAYEM BIN SALIM",
    "password": "q85H7AsLFs5J"
  },
  {
    "roll": "2403174",
    "name": "MD. ERAM OHID",
    "password": "Pg9kOoFM453g"
  },
  {
    "roll": "2403175",
    "name": "SARA ARPA",
    "password": "GZU4taLDn1bu"
  },
  {
    "roll": "2403176",
    "name": "JANNATUL MAWA TANHA",
    "password": "Kfw2pqFeTb3e"
  },
  {
    "roll": "2403177",
    "name": "MD.SAHARIAR JOY",
    "password": "htF5fMfXx6dZ"
  },
  {
    "roll": "2403178",
    "name": "ANUPAM ANJUM SHAHITYA",
    "password": "OiogLzaGV8qd"
  },
  {
    "roll": "2403179",
    "name": "FARDIN BIN ASLAM NUMAN",
    "password": "kQOkLja4EPyS"
  },
  {
    "roll": "2403180",
    "name": "A Q M MAHDI HAQUE",
    "password": "qe57A0NJWB0y"
  }
]
